.gitattributes
.gitignore
AUTHORS
MANIFEST.in
Makefile.am
NEWS
README
autogen.sh
configure.ac
gitrev.m4
i18n.h
setup.py
doc/Makefile.am
doc/chrysalide.1
pixmaps/Makefile.am
pixmaps/before-after.png
pixmaps/bookmark.png
pixmaps/breakpoint.png
pixmaps/breakpoint_disabled.png
pixmaps/breakpoint_normal.png
pixmaps/chrysalide-128.png
pixmaps/chrysalide-32.png
pixmaps/chrysalide-64.png
pixmaps/chrysalide-full.png
pixmaps/chrysalide-logo.svg
pixmaps/chrysalide.xcf
pixmaps/chrysalide_128.png
pixmaps/chrysalide_32.png
pixmaps/chrysalide_64.png
pixmaps/chrysalide_text.png
pixmaps/chrysalide_text.xcf
pixmaps/collapse.png
pixmaps/collapse_dark.png
pixmaps/entry.png
pixmaps/entrypoint.png
pixmaps/error_cpu.png
pixmaps/error_cpu.xcf
pixmaps/error_display.png
pixmaps/error_display.xcf
pixmaps/error_file.png
pixmaps/error_file.xcf
pixmaps/expand.png
pixmaps/expand_dark.png
pixmaps/openida.png
pixmaps/openida.xcf
pixmaps/openida_text.png
pixmaps/openida_text.xcf
pixmaps/palette.png
pixmaps/revision.png
pixmaps/revision_0.png
pixmaps/revision_1.png
pixmaps/revision_2.png
pixmaps/revision_3.png
pixmaps/revision_4.png
pixmaps/revision_5.png
pixmaps/revision_6.png
pixmaps/revision_7.png
pixmaps/revision_8.png
pixmaps/revision_9.png
pixmaps/snapshot.png
pixmaps/snapshot.xcf
pixmaps/snapshot_current.png
pixmaps/stopped.png
pixmaps/symbol_class_classic.png
pixmaps/symbol_object_classic.png
pixmaps/symbol_package.png
pixmaps/symbol_routine_classic.png
pixmaps/tbutton_collapse.png
pixmaps/tbutton_expand.png
pixmaps/tbutton_list_view.png
pixmaps/tbutton_tree_view.png
pixmaps/tipoftheday.png
pixmaps/tipoftheday.xcf
pixmaps/welcome.png
plugins/Makefile.am
plugins/androhelpers/Makefile.am
plugins/androhelpers/androhelpers.c
plugins/androhelpers/androhelpers.h
plugins/androhelpers/params.c
plugins/androhelpers/params.h
plugins/androhelpers/switch.c
plugins/androhelpers/switch.h
plugins/androhelpers/try_n_catch.c
plugins/androhelpers/try_n_catch.h
plugins/arm/Makefile.am
plugins/arm/cond.h
pychrysalide.egg-info/PKG-INFO
pychrysalide.egg-info/SOURCES.txt
pychrysalide.egg-info/dependency_links.txt
pychrysalide.egg-info/requires.txt
pychrysalide.egg-info/top_level.txt
