Metadata-Version: 2.1
Name: pychrysalide
Version: 2054
Summary: Reverse Engineering Factory
Home-page: https://www.chrysalide.re/
Author: Cyrille BAGARD
Author-email: nocbos@gmail.com
Project-URL: Bug Reports, https://bugs.chrysalide.re/
Project-URL: Source, http://git.0xdeadc0de.fr/cgi-bin/cgit.cgi/chrysalide.git/
Project-URL: Twitter, https://twitter.com/chrysalide_ref
Keywords: reverse,engineering,disassembler,security
Classifier: Development Status :: 3 - Alpha
Classifier: Environment :: Console
Classifier: Intended Audience :: Information Technology
Classifier: License :: OSI Approved :: GNU General Public License v3 (GPLv3)
Classifier: Programming Language :: C
Classifier: Programming Language :: Python :: 3
Classifier: Topic :: Security
Classifier: Topic :: Software Development :: Debuggers
Classifier: Topic :: Software Development :: Disassemblers
Classifier: Topic :: Software Development :: Embedded Systems
Requires-Python: >=3
License-File: AUTHORS
